{
  "locale": {
    "no_translation": "Dēļ mājaslapas vides, vienīgā officiālā satura versija ir Angļu valodā."
  },
  "index": {
    "tagline": "Atrodi, spēlē, un izveido Minecraft saturu",
    "description": "Atrodi izbaudāmu un augstas kvalitātes saturu izmantojot mūsu atvērtā primkoda modificēšanas platformu veidota kopienai. Izveido lietas, iegūsti algu*, un publicē savu projektu ar mūsu dokumentēto API!",
    "features": {
      "book": {
        "title": "Viegli izmantojams API",
        "description": "Pilnīgi dokumentēts API atvieglojot trešo partiju integrāciju un palaidēju pieaugumu."
      },
      "coin": {
        "title": "Satura veidotāju algas",
        "description": "Plānojam dot satura veidotājiem 100% reklāmu ieņēmumumus no viņu projektu lapām. *Pie algām vēl tiek strādāts."
      },
      "speedometer": {
        "title": "Zibenīgi ātra meklēšana",
        "description": "Darbināts ar ātriem un pielāgojamiem meklēšanas algoritmiem lai jums nav jāgaida."
      },
      "chat": {
        "title": "Izpalīdzīga kopiena",
        "description": "Iegūsti atbalstu, izstrādā, un atpūtieties mūsu Discord serverī ar pāri 1,500 dalībniekiem."
      },
      "puzzle": {
        "title": "Izplatāms pēc dizaina",
        "description": "Integrējās ar būvēšanas rīkiem, glabātuvēm, palaidējiem, un trešo partiju programmām."
      },
      "tools": {
        "title": "Pilnīgi atvērts pirmkods",
        "description": "Atvērta pirmkoda projekts kuru uztur aktīva kopiena kura aicina ieguldījumus."
      }
    }
  },
  "header": {
    "my_profile": "Aiziet uz savu profilu",
    "logout": "Izrakstīties",
    "github": "Pierakstīties ar GitHub"
  },
  "footer": {
    "description": "Modrinth is atvērta pirmkoda programmatūra.",
    "legal": {
      "heading": "Legālie",
      "terms": "Nosacījumi",
      "privacy": "Konfidencialitāte",
      "rules": "Noteikumi"
    },
    "resources": {
      "heading": "Resursi",
      "blog": "Blogs",
      "docs": "Dokumentācija"
    },
    "buttons": {
      "privacy": "Iestatīt konfidencialitātes prefrrences",
      "theme": {
        "label": "Mainīt motīvu",
        "system": "Sistēmas motīvs",
        "light": "Gaišais režīms",
        "dark": "Tumšais režīms",
        "oled": "OLED režīms"
      },
      "language": {
        "label": "Izvēlēties valodu"
      }
    }
  },
  "error": {
    "status": "{status} Kļūda",
    "message": {
      "404": "Ak nē, izskatās ka pazudāt [Labirintā](https://github.com/modrinth/labrinth).",
      "project_missing": "{type} ko meklējāt netika atrasts(a).",
      "default": "Notika negaidīta kļūda."
    },
    "actions": {
      "home": "Atgriezties",
      "discord": "Iegūt palīdzību Discord serverī"
    }
  },
  "pages": {
    "description": "Apraksts",
    "gallery": "Galerija",
    "changelog": "Izmaiņas",
    "versions": "Versijas",
    "settings": "Iestatījumi",
    "moderation": "Moderācija",
    "notifications": "Paziņojumi",
    "about": "Par",
    "following": "Sekojat",
    "terms": "Noteikumi un nosacījumi",
    "privacy": "Privātuma politika",
    "rules": "Projektu noteikumi",
    "all": "Visi"
  },
  "generic": {
    "labels": {
      "license": {
        "singular": "Licence",
        "plural": "Licences"
      },
      "project_id": "Projekta ID",
      "project_status": "Projekta statuss",
      "minecraft_versions": "Minecraft versijas",
      "mod_loaders": "Modu lādētāji",
      "categories": "Kategorijas",
      "downloads": "Lejupielādes",
      "files": "Faili"
    },
    "actions": {
      "create": "Izveidot",
      "edit": "Rediģēt",
      "follow": "Sekot",
      "unfollow": "Pārstāt sekot",
      "feature": "Ieteikt versiju",
      "report": "Ziņot",
      "new_project": "Jauns projekts",
      "preview": "Priekšskatījums",
      "download": "Lejupielādēt",
      "save": "Saglabāt",
      "confirm": "Apstiprināt",
      "remove": "Noņemt",
      "delete": "Dzēst",
      "cancel": "Atcelt",
      "discard": "Atmest izmaiņas"
    },
    "external": {
      "github_profile": "GitHub profils",
      "discord": "Discord",
      "github": "GitHub",
      "issues": "Problēmas",
      "source": "Pirmkods",
      "wiki": "Wiki",
      "patreon": "Patreon",
      "paypal": "PayPal",
      "buy_me_a_coffee": "Buy Me a Coffee",
      "github_sponsors": "GitHub Sponsori",
      "donate": "Ziedot",
      "kofi": "Ko-fi"
    },
    "environments": {
      "singular": "Vide",
      "plural": "Vides",
      "server_side": "Serveris",
      "client_side": "Klients",
      "values": {
        "required": "Nepieciešams",
        "unsupported": "Neatbalstīts",
        "optional": "Pēc izvēles",
        "unknown": "Nezināms"
      }
    },
    "up_to_date": "Jums nav paziņojumu!",
    "byline": "veidoja <u>{author}</u>"
  },
  "project": {
    "types": {
      "mod": {
        "singular": "Mods",
        "plural": "Modi",
        "search": "Meklēt modus..."
      },
      "modpack": {
        "singular": "Modpaka",
        "plural": "Modpakas",
        "search": "Meklēt modpakas..."
      }
    },
    "sidebar_headings": {
      "external_resources": "Ārējie resursi",
      "featured_versions": "Ieteiktās versijas",
      "project_members": "Projekta dalībnieki",
      "technical_information": "Tehniskā informācija"
    },
    "gallery": {
      "upload": "Augšupielādēt galerijas attēlu",
      "placeholder": {
        "title": "Ievadiet attēla virsrakstu...",
        "description": "Ievadiet attēla aprakstu..."
      }
    },
    "versions": {
      "upload": "Augšupielādēt jaunu versiju"
    },
    "body": {
      "editor": "Redaktors",
      "placeholder": "Ievadiet projekta aprakstu...",
      "empty": "Šis projekta apraksts ir tukšs."
    },
    "members": "Dalībnieki",
    "permissions": "Atļaujas",
    "permission": {
      "upload_version": "Augšupielādēt versiju",
      "delete_version": "Izdzēst versiju",
      "edit_details": "Rediģēt detaļas",
      "edit_body": "Rediģēt aprakstu",
      "manage_invites": "Pārvaldīt aicinājumus",
      "remove_member": "Noņemt dalībniekus",
      "edit_member": "Pārvaldīt dalībniekus",
      "delete_project": "Izdzēst projektu"
    },
    "role": {
      "text": "Loma",
      "placeholder": "Ievadiet lomas..."
    },
    "advanced": "Papildu",
    "visibility": {
      "title": "Redzamība",
      "description": "Šis projekts pašlaik ir {status}.",
      "action": "Mainīt redzamību"
    },
    "ownership": {
      "title": "Pārvaldīšanas tiesības",
      "description": "Nodot pārvaldīšanas tiesības citam lietotājam.",
      "action": "Nodot pārvaldīšanas tiesības"
    }
  },
  "version": {
    "featured": "Piedāvātie",
    "autofeatured": "Automātiski piedāvāts",
    "feature_action": "Funkcija",
    "dependencies": "Atkarības",
    "metadata": "Meta dati",
    "release_channel": "Izlaišanas kanāls",
    "number": "Versijas numurs",
    "publication_date": "Publikācijas datums",
    "publisher": "Izdevējs"
  },
  "search": {
    "filters": {
      "clear": "Noņemt filtrus",
      "hide": "Paslēpt filtrus",
      "show": "Rādīt filtrus",
      "show_snapshots": "Rādīt snapšotus",
      "search_versions": "Meklēt versijas...",
      "licenses": "Licences"
    },
    "sort": {
      "by": "Kārtot pēc",
      "relevance": "Atbilstība",
      "downloads": "Lejupielāžu skaits",
      "follows": "Sekotāju skaits",
      "newest": "Nesen izveidots",
      "updated": "Nesen atjaunināts"
    },
    "per_page": "Katrā lapā rādīt"
  },
  "status": {
    "approved": "Apstiprināts",
    "rejected": "Noraidīts",
    "draft": "Melnraksts",
    "unlisted": "Nerindots",
    "processing": "Zem pārbaudes",
    "unknown": "Nezināms"
  },
  "release_channels": {
    "release": "Izlaidums",
    "beta": "Beta",
    "alpha": "Alfa"
  },
  "roles": {
    "developer": "Izstrādātājs",
    "admin": "Administrators",
    "moderator": "Moderators"
  },
  "stats": {
    "joined": "Pievienojās {ago}",
    "notified": "Paziņots {ago}",
    "downloads": "{downloads, plural,one {<b>#</b> lejupielāde} other {<b>#</b> lejupielādes}}",
    "followers_of_projects": "{followers, plural,one {<b>#</b> projektu sekotājs} other {<b>#</b> projektu sekotāji}}",
    "followers": "{followers, plural,one {<b>#</b> sekotājs} other {<b>#</b> sekotāji}}",
    "user_id": "Lietotāja ID: {id}",
    "created": "Izveidots {ago}",
    "updated": "Atjaunināts {ago}"
  },
  "settings": {
    "username": {
      "text": "Lietotājvārds",
      "placeholder": "Pievienojiet lietotājvārdu..."
    },
    "bio": {
      "text": "Apraksts",
      "placeholder": "Pievienojiet aprakstu..."
    },
    "email": {
      "text": "Privātais e-pasts",
      "helper": "Tikai redzams moderatoriem.",
      "placeholder": "Pievienojiet e-pastu..."
    },
    "avatar": "Augšupielādēt profila attēlu"
  },
  "report": {
    "singular": "Ziņot",
    "plural": "Pārskati",
    "type": {
      "spam": "Spams",
      "copyright": "Autortiesības",
      "inappropriate": "Nepiemērots",
      "malicious": "Ļaunprātība",
      "name-squatting": "Vārda apmelošana",
      "other": "Cits"
    }
  },
  "user": {
    "following": {
      "loading": "Ielādē projektus kuriem tiek sekots...",
      "none": "Jūs neesat sekojis nevienam projektam."
    },
    "delete": {
      "title": "Dzēst kontu",
      "body": "Once you delete your account, there is no going back. Deleting your account will remove all attached data, including projects, from our servers."
    },
    "auth": {
      "title": "Authorization token",
      "body": "Your authorization token can be used with the Modrinth API, the Minotaur Gradle plugin, and other applications that interact with Modrinth's API. Be sure to keep this secret!",
      "copy": "Copy token to clipboard",
      "copied": "Copied token to clipboard",
      "revoke": "Revoke token"
    },
    "revoke_token": {
      "title": "Revoke your Modrinth token",
      "body": "Revoking your Modrinth token can have unintended consequences. Please be aware that the following could break:\n - Any application that uses your token to access the API.\n - Gradle - if Minotaur is given a incorrect token, your Gradle builds could fail.\n - GitHub - if you use a GitHub action that uses the Modrinth API, it will cause errors.\n\nIf you are willing to continue, complete the following steps:\n\n 1. Head to the [Modrinth Application page on GitHub](https://github.com/settings/connections/applications/3acffb2e808d16d4b226). Make sure to be logged into the GitHub account you used for Modrinth!\n 2. Press the big red \"Revoke Access\" button next to the \"Permissions\" header.\n\nOnce you have completed those steps, press the \"Log out\" button below.\n\n**This will log you out of Modrinth, however, when you log back in, your token will be regenerated.**",
      "action": "Log out"
    }
  },
  "images": {
    "replace": "Replace image",
    "how_to": "Drag and drop to upload or click to select"
  },
  "ads": {
    "privacy_respecting": "A privacy-respecting ad would have been shown here.",
    "console": {
      "line1": "You are using an adblocker.",
      "line2": "Your adblocker prevented Modrinth from showing an ad, our only source of income.",
      "line3": "If you still want to help Modrinth without viewing ads, you can contribute to Modrinth on GitHub!",
      "line4": "https://github.com/modrinth/"
    }
  },
  "modal": {
    "deletion": {
      "generic": {
        "important": "This is extremely important.",
        "verify": "To verify, type <i>{key}</i> below:",
        "placeholder": "Type here..."
      },
      "project": {
        "title": "Delete project",
        "description": "Deleting a project erases all project data, including versions.",
        "action": "Delete project"
      },
      "version": {
        "title": "Delete version",
        "description": "Are you sure you want to delete this version? All files and metadata will be irrecoverably lost.",
        "action": "Delete version"
      },
      "account": {
        "title": "Are you sure you want to do this?",
        "description": "This will **immediately delete all of your projects** and follows. Deleting your account cannot be reversed.\n\nIf you need help with your account, get support on the [Modrinth Discord](/discord).",
        "action": "Yes, irrecoverably delete my account"
      },
      "image": {
        "title": "Delete gallery image",
        "description": "Are you sure you want to delete this image file and metadata? This action cannot be undone.",
        "action": "Delete image"
      }
    },
    "report": {
      "generic": {
        "description": "Modding should be safe for everyone, so we take abuse and malicious intent seriously at Modrinth. We want to hear about harmful content on the site that violates our [ToS](/legal/terms) and [Rules](/legal/rules). Rest assured, we’ll keep your identifying information private.",
        "fields": {
          "reason": {
            "label": "Reason"
          },
          "information": {
            "label": "Additional information",
            "helper": "Include links and images if possible. Markdown formatting is supported.",
            "placeholder": "Enter additional information..."
          }
        }
      },
      "project": {
        "action": "Report project"
      },
      "version": {
        "action": "Report version"
      },
      "user": {
        "action": "Report user"
      }
    },
    "creation": {
      "project": {
        "title": "Create project",
        "description": "New projects are created as drafts, and can be found under your profile page.",
        "action": "Continue",
        "fields": {
          "project_type": {
            "label": "Project type"
          },
          "name": {
            "label": "Name",
            "placeholder": "Enter project name..."
          },
          "summary": {
            "label": "Summary",
            "helper": "This appears in search and on the sidebar of your project's page.",
            "placeholder": "Enter short summary of project..."
          }
        }
      },
      "image": {
        "title": "Add gallery image",
        "action": "Add image",
        "fields": {
          "title": {
            "label": "Title",
            "placeholder": "Ievadiet attēla virsrakstu..."
          },
          "description": {
            "label": "Apraksts",
            "placeholder": "Ievadiet attēla aprakstu..."
          }
        }
      }
    },
    "moderation": {
      "project_status": {
        "title": "Mainīt projekta statusu",
        "action": "Apstiprināt",
        "fields": {
          "status": {
            "label": "Statuss",
            "options": {
              "approve": "Apstiprināt",
              "unlist": "Nerindot",
              "reject": "Noraidīt"
            }
          },
          "moderation_message": {
            "label": "Moderācijas ziņa",
            "helper": "Pēc izvēles pievienot informāciju lai labotu problēmas ar projekta dalībniekiem. Markdown formatēšana ir atbalstīta.",
            "placeholder": "Ievadiet papildus informāciju..."
          }
        }
      }
    }
  },
  "tags": {
    "technology": "Tehnoloģijas",
    "adventure": "Adventure",
    "magic": "Magic",
    "utility": "Utility",
    "decoration": "Decoration",
    "library": "Library",
    "cursed": "Cursed",
    "worldgen": "World generation",
    "storage": "Storage",
    "food": "Food",
    "equipment": "Equipment",
    "miscellaneous": "Miscellaneous",
    "challenging": "Challenging",
    "combat": "Combat",
    "kitchen-sink": "Kitchen Sink",
    "lightweight": "Lightweight",
    "multiplayer": "Multiplayer",
    "quests": "Quests",
    "optimization": "Optimization",
    "fabric": "Fabric",
    "forge": "Forge",
    "quilt": "Quilt",
    "modloader": "ModLoader",
    "rift": "Rift",
    "server": "Server",
    "client": "Client",
    "good": "Good",
    "trash": "Trash",
    "misc": "Miscellaneous"
  }
}
